blueprint/__init__.py
blueprint/cli.py
blueprint/config.py
blueprint/core.py
blueprint/errors.py
blueprint/loaders.py
blueprint/models.py
blueprint/py.typed
blueprint/registry.py
blueprint/template_loader.py
blueprint/utils.py
blueprint/templates/blueprint.toml.template
blueprint/templates/dag_loader.py.template
blueprint/templates/example_etl.py.template
airflow_blueprint-0.0.1a3.dist-info/METADATA
airflow_blueprint-0.0.1a3.dist-info/WHEEL
airflow_blueprint-0.0.1a3.dist-info/entry_points.txt
airflow_blueprint-0.0.1a3.dist-info/RECORD
