Metadata-Version: 2.4
Name: airflow-blueprint
Version: 0.0.1a3
Summary: Create reusable Airflow DAG templates with validated configurations
Project-URL: Homepage, https://github.com/astronomer/blueprint
Project-URL: Repository, https://github.com/astronomer/blueprint
Project-URL: Documentation, https://docs.astronomer.io/blueprint
Author-email: Astronomer <humans@astronomer.io>
Maintainer-email: Astronomer <humans@astronomer.io>
License: MIT
Keywords: airflow,automation,blueprints,dags,templates
Classifier: Development Status :: 3 - Alpha
Classifier: Framework :: Apache Airflow
Classifier: Intended Audience :: Developers
Classifier: License :: OSI Approved :: MIT License
Classifier: Operating System :: OS Independent
Classifier: Programming Language :: Python :: 3
Classifier: Programming Language :: Python :: 3.8
Classifier: Programming Language :: Python :: 3.9
Classifier: Programming Language :: Python :: 3.10
Classifier: Programming Language :: Python :: 3.11
Classifier: Programming Language :: Python :: 3.12
Classifier: Topic :: Software Development :: Libraries :: Python Modules
Classifier: Topic :: System :: Systems Administration
Requires-Python: >=3.8
Requires-Dist: apache-airflow>=2.5.0
Requires-Dist: click>=8.0.0
Requires-Dist: pydantic>=2.10.6
Requires-Dist: pyyaml>=6.0
Requires-Dist: rich>=13.9.4
Requires-Dist: typing-extensions>=4.0.0; python_version < '3.9'
